multi_search_api/__init__.py
multi_search_api/cache.py
multi_search_api/core.py
multi_search_api/exceptions.py
multi_search_api/providers/__init__.py
multi_search_api/providers/base.py
multi_search_api/providers/brave.py
multi_search_api/providers/duckduckgo.py
multi_search_api/providers/google_scraper.py
multi_search_api/providers/ollama.py
multi_search_api/providers/searxng.py
multi_search_api/providers/serper.py
multi_search_api-0.1.11.dist-info/licenses/LICENSE
multi_search_api-0.1.11.dist-info/METADATA
multi_search_api-0.1.11.dist-info/WHEEL
multi_search_api-0.1.11.dist-info/top_level.txt
multi_search_api-0.1.11.dist-info/RECORD
