Metadata-Version: 2.4
Name: multi-search-api
Version: 0.1.11
Summary: Intelligent multi-provider search API with automatic fallback and caching
Author-email: Joop Snijder <joop@example.com>
License: MIT
Project-URL: Homepage, https://github.com/Joopsnijder/multi-search-api
Project-URL: Documentation, https://github.com/Joopsnijder/multi-search-api#readme
Project-URL: Repository, https://github.com/Joopsnijder/multi-search-api
Project-URL: Issues, https://github.com/Joopsnijder/multi-search-api/issues
Keywords: search,api,serper,brave,searxng,web-search,multi-provider
Classifier: Development Status :: 4 - Beta
Classifier: Intended Audience :: Developers
Classifier: License :: OSI Approved :: MIT License
Classifier: Programming Language :: Python :: 3
Classifier: Programming Language :: Python :: 3.10
Classifier: Programming Language :: Python :: 3.11
Classifier: Programming Language :: Python :: 3.12
Classifier: Programming Language :: Python :: 3.13
Classifier: Topic :: Internet :: WWW/HTTP :: Indexing/Search
Classifier: Topic :: Software Development :: Libraries :: Python Modules
Requires-Python: >=3.10
License-File: LICENSE
Requires-Dist: httpx>=0.27.0
Requires-Dist: requests>=2.31.0
Requires-Dist: justhtml>=0.1.0
Requires-Dist: python-dotenv>=1.0.0
Requires-Dist: ddgs>=6.0.0
Provides-Extra: dev
Requires-Dist: pytest>=7.0.0; extra == "dev"
Requires-Dist: pytest-cov>=4.0.0; extra == "dev"
Requires-Dist: pytest-mock>=3.12.0; extra == "dev"
Requires-Dist: freezegun>=1.4.0; extra == "dev"
Requires-Dist: responses>=0.24.0; extra == "dev"
Requires-Dist: ruff>=0.1.0; extra == "dev"
Requires-Dist: build>=1.0.0; extra == "dev"
Requires-Dist: twine>=4.0.0; extra == "dev"
Dynamic: license-file
